fast_fig/__init__.py
fast_fig/class_ffig.py
fast_fig/presets.py
fast_fig-0.8.1.dist-info/licenses/LICENSE
fast_fig-0.8.1.dist-info/METADATA
fast_fig-0.8.1.dist-info/WHEEL
fast_fig-0.8.1.dist-info/top_level.txt
fast_fig-0.8.1.dist-info/RECORD
