Metadata-Version: 2.4
Name: fast_fig
Version: 0.8.1
Summary: FaSt_Fig is a wrapper for matplotlib with templates.
Author-email: Fabian Stutzki <fast@fast-apps.de>
License-Expression: MIT
Keywords: matplotlib,figure
Classifier: Programming Language :: Python :: 3
Classifier: Operating System :: OS Independent
Requires-Python: >=3.9
License-File: LICENSE
Requires-Dist: numpy>=1.26.0
Requires-Dist: matplotlib>=3.6.0
Requires-Dist: pandas>=2.1.0
Requires-Dist: pyyaml>=6.0.2
Requires-Dist: logging>=0.4.0
Requires-Dist: pathlib>=1.0.0
Requires-Dist: typing-extensions>=4.0.0
Dynamic: license-file
